{
  "info": {
    "name": "Laravel API - Users",
    "_postman_id": "12345678-abcd-efgh-ijkl-1234567890ab",
    "description": "Cole\u00e7\u00e3o de testes para a API de gerenciamento de usu\u00e1rios.",
    "schema": "https://schema.getpostman.com/json/collection/v2.1.0/collection.json"
  },
  "item": [
    {
      "name": "Listar usu\u00e1rios",
      "request": {
        "method": "GET",
        "header": [],
        "url": {
          "raw": "http://localhost:8000/api/users",
          "protocol": "http",
          "host": [
            "localhost"
          ],
          "port": "8000",
          "path": [
            "api",
            "users"
          ]
        }
      }
    },
    {
      "name": "Criar usu\u00e1rio",
      "request": {
        "method": "POST",
        "header": [
          {
            "key": "Content-Type",
            "value": "application/json"
          }
        ],
        "body": {
          "mode": "raw",
          "raw": "{\n  \"name\": \"Jo\\u00e3o da Silva\",\n  \"email\": \"joao@email.com\",\n  \"phone\": \"(11) 99999-0000\"\n}"
        },
        "url": {
          "raw": "http://localhost:8000/api/users",
          "protocol": "http",
          "host": [
            "localhost"
          ],
          "port": "8000",
          "path": [
            "api",
            "users"
          ]
        }
      }
    },
    {
      "name": "Detalhes de um usu\u00e1rio",
      "request": {
        "method": "GET",
        "header": [],
        "url": {
          "raw": "http://localhost:8000/api/users/1",
          "protocol": "http",
          "host": [
            "localhost"
          ],
          "port": "8000",
          "path": [
            "api",
            "users",
            "1"
          ]
        }
      }
    }
  ]
}